colcon_ros_bundle/__init__.py
colcon_ros_bundle/installer/__init__.py
colcon_ros_bundle/installer/rdmanifest.py
colcon_ros_bundle/task/__init__.py
colcon_ros_bundle/task/ros_bundle.py
colcon_ros_bundle/task/ament/__init__.py
colcon_ros_bundle/task/ament/bundle.py
colcon_ros_bundle/task/ament_python/__init__.py
colcon_ros_bundle/task/ament_python/bundle.py
colcon_ros_bundle/task/catkin/__init__.py
colcon_ros_bundle/task/catkin/_rosdep.py
colcon_ros_bundle/task/catkin/bundle.py
colcon_ros_bundle/task/cmake/__init__.py
colcon_ros_bundle/task/cmake/bundle.py
colcon_ros_bundle-0.1.1.dist-info/LICENSE
colcon_ros_bundle-0.1.1.dist-info/METADATA
colcon_ros_bundle-0.1.1.dist-info/NOTICE
colcon_ros_bundle-0.1.1.dist-info/WHEEL
colcon_ros_bundle-0.1.1.dist-info/entry_points.txt
colcon_ros_bundle-0.1.1.dist-info/top_level.txt
colcon_ros_bundle-0.1.1.dist-info/zip-safe
colcon_ros_bundle-0.1.1.dist-info/RECORD
