Metadata-Version: 2.1
Name: colcon-ros-bundle
Version: 0.1.1
Summary: Plugin for colcon to bundle ros applications
Home-page: UNKNOWN
Author: Matthew Murphy
Author-email: matmur@amazon.com
Maintainer: Matthew Murphy
Maintainer-email: matmur@amazon.com
License: Apache License, Version 2.0
Project-URL: Changelog, https://github.com/colcon/colcon-bundle/milestones?direction=desc&sort=due_date&state=closed
Project-URL: GitHub, https://github.com/colcon/colcon-bundle/
Keywords: colcon
Platform: UNKNOWN
Classifier: Development Status :: 3 - Alpha
Classifier: Environment :: Console
Classifier: Intended Audience :: Developers
Classifier: License :: OSI Approved :: Apache Software License
Classifier: Operating System :: MacOS
Classifier: Operating System :: Microsoft :: Windows
Classifier: Operating System :: POSIX
Classifier: Programming Language :: Python
Classifier: Topic :: Software Development :: Build Tools
Requires-Python: >=3.5
Requires-Dist: colcon-bundle (>=0.0.18)
Requires-Dist: colcon-ros (>=0.3.5)
Requires-Dist: rosdep (>=0.14.0)
Requires-Dist: setuptools (>=30.3.0)
